{
  "info": {
    "_postman_id": "d5be1d33-bf29-4386-8306-1cfcd6b3a83e",
    "name": "ReqRes API - QA Practice",
    "schema": "https://schema.getpostman.com/json/collection/v2.1.0/collection.json",
    "_exporter_id": "48636555",
    "_collection_link": "https://go.postman.co/collection/48636555-d5be1d33-bf29-4386-8306-1cfcd6b3a83e?source=collection_link"
  },
  "item": [
    {
      "name": "USUARIOS",
      "item": [
        {
          "name": "Eliminar usuario",
          "item": [
            {
              "name": "https://reqres.in/api/users/2",
              "event": [
                {
                  "listen": "test",
                  "script": {
                    "exec": [
                      "pm.test(\"Status code is 204\", function () {\r",
                      "    pm.response.to.have.status(204);\r",
                      "});"
                    ],
                    "type": "text/javascript",
                    "packages": {},
                    "requests": {}
                  }
                }
              ],
              "request": {
                "auth": {
                  "type": "noauth"
                },
                "method": "DELETE",
                "header": [
                  {
                    "key": "x-api-key",
                    "value": "{{api_key}}",
                    "type": "text"
                  },
                  {
                    "key": "",
                    "value": "",
                    "type": "text",
                    "disabled": true
                  }
                ],
                "body": {
                  "mode": "raw",
                  "raw": "{\r\n  \"name\": \"Facundo\",\r\n  \"job\": \"QA Tester\"\r\n}"
                },
                "url": {
                  "raw": "{{base_url}}/api/users/2",
                  "host": [
                    "{{base_url}}"
                  ],
                  "path": [
                    "api",
                    "users",
                    "2"
                  ]
                }
              },
              "response": []
            }
          ]
        },
        {
          "name": "Actualizar usuario",
          "item": [
            {
              "name": "https://reqres.in/api/users/2",
              "event": [
                {
                  "listen": "test",
                  "script": {
                    "exec": [
                      "pm.test(\"Status code is 200\", function () {\r",
                      "    pm.response.to.have.status(200);\r",
                      "});\r",
                      "\r",
                      "pm.test(\"Job was updated\", function () {\r",
                      "    var json = pm.response.json();\r",
                      "    pm.expect(json.job).to.eql(\"QA Engineer\");\r",
                      "});"
                    ],
                    "type": "text/javascript",
                    "packages": {},
                    "requests": {}
                  }
                }
              ],
              "request": {
                "auth": {
                  "type": "noauth"
                },
                "method": "PUT",
                "header": [
                  {
                    "key": "x-api-key",
                    "value": "free_user_30MBD6INigdmUDbEScFiGzHhrpd",
                    "type": "text"
                  }
                ],
                "body": {
                  "mode": "raw",
                  "raw": "{\r\n  \"name\": \"Facundo\",\r\n  \"job\": \"QA Engineer\"\r\n}",
                  "options": {
                    "raw": {
                      "language": "json"
                    }
                  }
                },
                "url": {
                  "raw": "https://reqres.in/api/users/2?api_key=reqres-free-v1",
                  "protocol": "https",
                  "host": [
                    "reqres",
                    "in"
                  ],
                  "path": [
                    "api",
                    "users",
                    "2"
                  ],
                  "query": [
                    {
                      "key": "api_key",
                      "value": "reqres-free-v1"
                    }
                  ]
                }
              },
              "response": []
            },
            {
              "name": "https://reqres.in/api/users/2",
              "event": [
                {
                  "listen": "test",
                  "script": {
                    "exec": [
                      "pm.test(\"Status code is 204\", function () {\r",
                      "    pm.response.to.have.status(204);\r",
                      "});"
                    ],
                    "type": "text/javascript",
                    "packages": {},
                    "requests": {}
                  }
                }
              ],
              "request": {
                "auth": {
                  "type": "noauth"
                },
                "method": "DELETE",
                "header": [
                  {
                    "key": "x-api-key",
                    "value": "free_user_30MBD6INigdmUDbEScFiGzHhrpd",
                    "type": "text"
                  },
                  {
                    "key": "",
                    "value": "",
                    "type": "text",
                    "disabled": true
                  }
                ],
                "body": {
                  "mode": "raw",
                  "raw": "{\r\n  \"name\": \"Facundo\",\r\n  \"job\": \"QA Tester\"\r\n}"
                },
                "url": {
                  "raw": "https://reqres.in/api/users/2",
                  "protocol": "https",
                  "host": [
                    "reqres",
                    "in"
                  ],
                  "path": [
                    "api",
                    "users",
                    "2"
                  ]
                }
              },
              "response": []
            }
          ]
        },
        {
          "name": "Usuario no encontrado - 404",
          "item": [
            {
              "name": "https://reqres.in/api/users/2",
              "event": [
                {
                  "listen": "test",
                  "script": {
                    "exec": [
                      "pm.test(\"Status code is 404\", function () {\r",
                      "    pm.response.to.have.status(404);\r",
                      "});"
                    ],
                    "type": "text/javascript",
                    "packages": {},
                    "requests": {}
                  }
                },
                {
                  "listen": "prerequest",
                  "script": {
                    "packages": {},
                    "type": "text/javascript"
                  }
                }
              ],
              "request": {
                "auth": {
                  "type": "noauth"
                },
                "method": "GET",
                "header": [
                  {
                    "key": "x-api-key",
                    "value": "{{api_key}}",
                    "type": "text"
                  }
                ],
                "url": {
                  "raw": "{{base_url}}/api/users/99",
                  "host": [
                    "{{base_url}}"
                  ],
                  "path": [
                    "api",
                    "users",
                    "99"
                  ]
                }
              },
              "response": []
            }
          ],
          "event": [
            {
              "listen": "prerequest",
              "script": {
                "type": "text/javascript",
                "packages": {},
                "requests": {},
                "exec": [
                  ""
                ]
              }
            },
            {
              "listen": "test",
              "script": {
                "type": "text/javascript",
                "packages": {},
                "requests": {},
                "exec": [
                  "pm.test(\"Status code is 404\", function () {\r",
                  "    pm.response.to.have.status(404);\r",
                  "});"
                ]
              }
            }
          ]
        },
        {
          "name": "obtener usuario por ID",
          "item": [
            {
              "name": "Obtener usuario por ID",
              "event": [
                {
                  "listen": "test",
                  "script": {
                    "exec": [
                      "pm.test(\"Status code is 200\", function () {\r",
                      "    pm.response.to.have.status(200);\r",
                      "});\r",
                      "\r",
                      "pm.test(\"User has email\", function () {\r",
                      "    var json = pm.response.json();\r",
                      "    pm.expect(json.data.email).to.exist;\r",
                      "});"
                    ],
                    "type": "text/javascript",
                    "packages": {},
                    "requests": {}
                  }
                }
              ],
              "protocolProfileBehavior": {
                "disableBodyPruning": true
              },
              "request": {
                "auth": {
                  "type": "noauth"
                },
                "method": "GET",
                "header": [
                  {
                    "key": "x-api-key",
                    "value": "{{api_key}}",
                    "type": "text"
                  },
                  {
                    "key": "",
                    "value": "",
                    "type": "text",
                    "disabled": true
                  }
                ],
                "body": {
                  "mode": "raw",
                  "raw": "{\r\n  \"name\": \"Facundo\",\r\n  \"job\": \"QA Tester\"\r\n}",
                  "options": {
                    "raw": {
                      "language": "json"
                    }
                  }
                },
                "url": {
                  "raw": "{{base_url}}/api/users/2",
                  "host": [
                    "{{base_url}}"
                  ],
                  "path": [
                    "api",
                    "users",
                    "2"
                  ]
                }
              },
              "response": []
            },
            {
              "name": "{{base_url}}/api/users/2",
              "event": [
                {
                  "listen": "test",
                  "script": {
                    "exec": [
                      "pm.test(\"Status code is 200\", function () {\r",
                      "    pm.response.to.have.status(200);\r",
                      "});\r",
                      "\r",
                      "pm.test(\"User has email\", function () {\r",
                      "    var json = pm.response.json();\r",
                      "    pm.expect(json.data.email).to.exist;\r",
                      "});"
                    ],
                    "type": "text/javascript",
                    "packages": {},
                    "requests": {}
                  }
                }
              ],
              "request": {
                "auth": {
                  "type": "noauth"
                },
                "method": "GET",
                "header": [
                  {
                    "key": "x-api-key",
                    "value": "{{api_key}}",
                    "type": "text"
                  }
                ],
                "url": {
                  "raw": "{{base_url}}/api/users/2",
                  "host": [
                    "{{base_url}}"
                  ],
                  "path": [
                    "api",
                    "users",
                    "2"
                  ]
                }
              },
              "response": []
            }
          ]
        }
      ]
    }
  ]
}